proto_schema_parser-2.0.0.dist-info/METADATA
proto_schema_parser-2.0.0.dist-info/WHEEL
proto_schema_parser-2.0.0.dist-info/entry_points.txt
proto_schema_parser-2.0.0.dist-info/licenses/LICENSE
proto_schema_parser/__init__.py
proto_schema_parser/antlr/ProtobufLexer.interp
proto_schema_parser/antlr/ProtobufLexer.py
proto_schema_parser/antlr/ProtobufLexer.tokens
proto_schema_parser/antlr/ProtobufParser.interp
proto_schema_parser/antlr/ProtobufParser.py
proto_schema_parser/antlr/ProtobufParser.tokens
proto_schema_parser/antlr/ProtobufParserListener.py
proto_schema_parser/antlr/ProtobufParserVisitor.py
proto_schema_parser/antlr/__init__.py
proto_schema_parser/ast.py
proto_schema_parser/generator.py
proto_schema_parser/parser.py
proto_schema_parser/py.typed
proto_schema_parser-2.0.0.dist-info/RECORD
