Metadata-Version: 2.1
Name: proto-schema-parser
Version: 2.0.0
Summary: A Pure Python Protobuf .proto Parser
Author-Email: Chris Riccomini <criccomini@apache.org>
License: MIT
Requires-Python: >=3.9
Requires-Dist: antlr4-python3-runtime>=4.13.0
